<?xml version="1.0" encoding="UTF-8"?>
<objects serializationModel="Studio.02.01.00">
	<object class="AudioFile" id="{bf549931-ef88-4b4e-a031-61a31c88f6a5}">
		<property name="assetPath">
			<value>Ground_Switch.wav</value>
		</property>
		<property name="frequencyInKHz">
			<value>48</value>
		</property>
		<property name="channelCount">
			<value>2</value>
		</property>
		<property name="length">
			<value>0.8203125</value>
		</property>
		<relationship name="masterAssetFolder">
			<destination>{ce571130-28bf-45c7-9f61-e92c0a9bdae9}</destination>
		</relationship>
	</object>
</objects>
